example_package/__init__.py
example_package/example.py
example_pkg_IronWallace-0.1.dist-info/LICENSE
example_pkg_IronWallace-0.1.dist-info/METADATA
example_pkg_IronWallace-0.1.dist-info/WHEEL
example_pkg_IronWallace-0.1.dist-info/top_level.txt
example_pkg_IronWallace-0.1.dist-info/RECORD
