Metadata-Version: 2.1
Name: example-pkg-IronWallace
Version: 0.1
Summary: A samll example package
Home-page: https://github.com/pypa/sampleproject
Author: Example Author
Author-email: author@example.com
License: UNKNOWN
Project-URL: Bug Tracker, https://github.com/pypa/sampleproject/issues
Platform: UNKNOWN
Requires-Python: >=3.6
License-File: LICENSE
